Metadata-Version: 2.2
Name: blackspammerbd_remot1
Version: 1.0.0
Summary: A CLI package for secure device connection and file transfer
Home-page: https://github.com/Blackspammerbd/blackspammerbd_remot1
Author: Shawpon Sp
Author-email: shawponsp6@gmail.com
Classifier: Programming Language :: Python :: 3
Classifier: Operating System :: OS Independent
License-File: LICENSE.chromedriver
Requires-Dist: colorama
Requires-Dist: requests
Dynamic: author
Dynamic: author-email
Dynamic: classifier
Dynamic: home-page
Dynamic: requires-dist
Dynamic: summary
